mdit_plain/renderer.py
mdit_plain-1.0.1.dist-info/LICENSE
mdit_plain-1.0.1.dist-info/METADATA
mdit_plain-1.0.1.dist-info/WHEEL
mdit_plain-1.0.1.dist-info/top_level.txt
mdit_plain-1.0.1.dist-info/RECORD
